
<alfresco-config>

    <config evaluator="string-compare" condition="Workflow">
        <hidden-workflows>
            <workflow name="activiti$newUserReview"/>
        </hidden-workflows>
    </config>


    <!--Forms-->
    <config evaluator="aspect" condition="fs-newUser:newUserAspect">
        <forms>
            <form>
                <field-visibility>
                    <show id="fs-newUser:answerDate"/>
                    <show id="fs-newUser:rejectReason"/>
                    <show id="fs-newUser:whoReviewed"/>
                </field-visibility>
                <appearance>
                    <field id="fs-newUser:answerDate" label-id-id="answerDate"/>
                    <field id="fs-newUser:whoReviewed" label-id="who reviewed"/>
                </appearance>
            </form>
        </forms>
    </config>

    <!--assign review group - form-->
    <config evaluator="model-type" condition="fs-forms:reviewUsers">
        <forms>
            <form>
                <field-visibility>
                </field-visibility>
                <appearance>
                    <field id="fs-forms:isRequired" label-id="prop.fs-forms_isRequired"
                           help-id="help.fs-forms_isRequired">
                    </field>

                    <field id="fs-forms:groupAssignee" label-id="assoc.fs-forms_groupAssignee"
                           help-id="help.fs-forms_groupAssignee">
                    </field>
                </appearance>
            </form>
        </forms>
    </config>

    <!--User review workflow-->
    <config evaluator="task-type" condition="fs-newUserRWF:userReviewingTask">
        <forms>
            <form>
                <field-visibility>
                    <show id="fs-forms:firstName"/>
                    <show id="fs-forms:lastName"/>
                    <show id="fs-forms:email"/>
                    <show id="fs-newUserRWF:doApprove"/>
                    <show id="fs-newUser:rejectReason"/>
                    <show id="transitions"/>
                </field-visibility>
                <appearance>
                    <field id="fs-forms:firstName" label-id="prop.fs-forms_firstName"/>
                    <field id="fs-forms:lastName" label-id="prop.fs-forms_lastName"/>
                    <field id="fs-forms:email" label-id="prop.fs-forms_email" read-only="true"/>
                    <field id="fs-newUserRWF:doApprove" label-id="prop.fs-newUserRWF_doApprove">
                        <control template="/org/alfresco/components/form/controls/doApproveWorkflow.ftl">
                        </control>
                    </field>

                    <field id="fs-newUser:rejectReason" label-id="prop.fs-newUser_rejectReason">
                        <control template="/org/alfresco/components/form/controls/rejectReasonWorkflow.ftl">
                        </control>
                    </field>

                    <field id="transitions">
                        <control template="/org/alfresco/components/form/controls/transitionsWorkflow.ftl">
                        </control>
                    </field>
                </appearance>
            </form>
        </forms>
    </config>
</alfresco-config>